ask_pypi/__init__.py
ask_pypi/__main__.py
ask_pypi/py.typed
ask_pypi/pypi_project.py
ask_pypi-0.6.0.dist-info/LICENSE.txt
ask_pypi-0.6.0.dist-info/METADATA
ask_pypi-0.6.0.dist-info/WHEEL
ask_pypi-0.6.0.dist-info/entry_points.txt
ask_pypi-0.6.0.dist-info/top_level.txt
ask_pypi-0.6.0.dist-info/RECORD
